multiwall/__init__.py
multiwall/__main__.py
multiwall/images.py
multiwall/multiwall.py
multiwall-1.8.dist-info/METADATA
multiwall-1.8.dist-info/WHEEL
multiwall-1.8.dist-info/top_level.txt
multiwall-1.8.dist-info/RECORD
